{
    "homepage": "https://pc.weixin.qq.com/",
    "description": "Wechat by Tencent",
    "license": "Commercial",
    "version": "4.0.6",
    "url": "https://dldir1v6.qq.com/weixin/Universal/Windows/WeChatWin.exe",
    "hash": "4257134c41e5bccc1c5b3eed30caab0139b5746a18504bb2a0ca9c3effebbeca",
    "installer": {
        "script": "Start-Process -FilePath \"$dir\\$fname\" -Verb RunAs | Wait-Process"
    },
    "checkver": {
        "url": "https://pc.weixin.qq.com/",
        "regex": "version=([\\d.]+)"
    },
    "autoupdate": {
        "url": "https://dldir1v6.qq.com/weixin/Universal/Windows/WeChatWin.exe"
    }
}
