{
    "version": "11.2.2.726",
    "description": "Free Registry Cleaner and Optimizer",
    "license": "https://www.wisecleaner.com",
    "homepage": "https://www.wisecleaner.com",
    "architecture": {
        "64bit": {
            "url": "https://downloads.wisecleaner.com/soft/WRCFree_11.2.2.726.zip",
            "hash": "6f575d44245e0c9a6218c0f163964415ad0101273e9052c9a882dd1377e7e88a",
            "extract_dir": "WRCFree_11.2.2.726"
        }
    },
    "bin": "WiseRegCleaner.exe",
    "shortcuts": [
        [
            "WiseRegCleaner.exe",
            "Wise Registry Cleaner"
        ]
    ],
    "checkver": {
        "url": "https://www.wisecleaner.com/download.html",
        "regex": "WRCFree_(?<version>[\\d\\.]+)\\.zip"
    },
    "autoupdate": {
        "architecture": {
            "64bit": {
                "url": "https://downloads.wisecleaner.com/soft/WRCFree_$version.zip",
                "extract_dir": "WRCFree_$version"
            }
        }
    }
}
