{
    "version": "10.6.2.798",
    "description": "Free Registry Cleaner and Optimizer",
    "license": "https://www.wisecleaner.com",
    "homepage": "https://www.wisecleaner.com",
    "architecture": {
        "64bit": {
            "url": "https://downloads.wisecleaner.com/soft/WDCFree_10.6.2.798.zip",
            "hash": "b5d61b8feed3b0188aabc0314e395b8c68c8716c0e3c643870e1d0c31f5fd9c5",
            "extract_dir": "Wise Disk Cleaner"
        }
    },
    "bin": "WiseDiskCleaner.exe",
    "shortcuts": [
        [
            "WiseDiskCleaner.exe",
            "Wise Disk Cleaner"
        ]
    ],
    "checkver": {
        "url": "https://www.wisecleaner.com/download.html",
        "regex": "WDCFree_(?<version>[\\d\\.]+)\\.zip"
    },
    "autoupdate": {
        "architecture": {
            "64bit": {
                "url": "https://downloads.wisecleaner.com/soft/WDCFree_$version.zip",
                "extract_dir": "Wise Disk Cleaner"
            }
        }
    }
}
